pyproject_bumper/__init__.py
pyproject_bumper/bumper.py
pyproject_bumper/cli.py
pyproject_bumper/exceptions.py
pyproject_bumper/formatters.py
pyproject_bumper/models.py
pyproject_bumper-3.2.0.dist-info/METADATA
pyproject_bumper-3.2.0.dist-info/WHEEL
pyproject_bumper-3.2.0.dist-info/entry_points.txt
pyproject_bumper-3.2.0.dist-info/RECORD
