Metadata-Version: 2.4
Name: pyproject-bumper
Version: 3.2.0
Summary: Add your description here
Author-email: alvaroroco <alvaroroco@gmail.com>
Requires-Python: >=3.9
Requires-Dist: loguru>=0.7.3
Requires-Dist: tomli-w>=1.2.0
Requires-Dist: tomli>=2.2.1
